nautobot_dns_records/__init__.py
nautobot_dns_records/api/__init__.py
nautobot_dns_records/api/serializers.py
nautobot_dns_records/api/urls.py
nautobot_dns_records/api/views.py
nautobot_dns_records/choices.py
nautobot_dns_records/filters.py
nautobot_dns_records/forms.py
nautobot_dns_records/homepage.py
nautobot_dns_records/migrations/0001_initial.py
nautobot_dns_records/migrations/0002_status.py
nautobot_dns_records/migrations/0003_constraints.py
nautobot_dns_records/migrations/0004_auto_20250108_0728.py
nautobot_dns_records/migrations/0005_alter_addressrecord_status_alter_cnamerecord_status_and_more.py
nautobot_dns_records/migrations/0006_remove_ptrrecord_ptr_unique_label_address_and_more.py
nautobot_dns_records/migrations/__init__.py
nautobot_dns_records/models.py
nautobot_dns_records/navigation.py
nautobot_dns_records/tables.py
nautobot_dns_records/template_content.py
nautobot_dns_records/templates/nautobot_dns_records/addressrecord.html
nautobot_dns_records/templates/nautobot_dns_records/addressrecord_edit.html
nautobot_dns_records/templates/nautobot_dns_records/cnamerecord.html
nautobot_dns_records/templates/nautobot_dns_records/locrecord.html
nautobot_dns_records/templates/nautobot_dns_records/ptrrecord.html
nautobot_dns_records/templates/nautobot_dns_records/srvrecord.html
nautobot_dns_records/templates/nautobot_dns_records/sshfprecord.html
nautobot_dns_records/templates/nautobot_dns_records/tab_device_records.html
nautobot_dns_records/templates/nautobot_dns_records/tab_ipaddress_records.html
nautobot_dns_records/templates/nautobot_dns_records/txtrecord.html
nautobot_dns_records/tests/__init__.py
nautobot_dns_records/tests/helpers.py
nautobot_dns_records/tests/mixins.py
nautobot_dns_records/tests/test_models.py
nautobot_dns_records/urls.py
nautobot_dns_records/validators.py
nautobot_dns_records/views/__init__.py
nautobot_dns_records/views/addressrecord.py
nautobot_dns_records/views/cnamerecord.py
nautobot_dns_records/views/device_tab.py
nautobot_dns_records-0.4.0.dist-info/LICENSE
nautobot_dns_records-0.4.0.dist-info/METADATA
nautobot_dns_records-0.4.0.dist-info/WHEEL
nautobot_dns_records-0.4.0.dist-info/RECORD
