Metadata-Version: 2.3
Name: nautobot-dns-records
Version: 0.4.0
Summary: Manage DNS Records in Nautobot
License: Apache-2.0
Author: Daniel Bacher
Author-email: bacher@kit.edu
Requires-Python: >=3.9,<3.12
Classifier: License :: OSI Approved :: Apache Software License
Classifier: Programming Language :: Python :: 3
Classifier: Programming Language :: Python :: 3.9
Classifier: Programming Language :: Python :: 3.10
Classifier: Programming Language :: Python :: 3.11
